sqlalchemy_flattener/__init__.py
sqlalchemy_flattener/__main__.py
sqlalchemy_flattener/flattener.py
sqlalchemy_flattener/writers.py
sqlalchemy_flattener-0.5.0.dist-info/METADATA
sqlalchemy_flattener-0.5.0.dist-info/WHEEL
sqlalchemy_flattener-0.5.0.dist-info/entry_points.txt
sqlalchemy_flattener-0.5.0.dist-info/licenses/LICENSE
sqlalchemy_flattener-0.5.0.dist-info/RECORD
