Metadata-Version: 2.4
Name: sqlalchemy-flattener
Version: 0.5.0
Summary: Flatten nested SQLAlchemy model data
Author-email: Michael Bosch <michael@vonbosch.co.za>
License-File: LICENSE
Requires-Python: <4.0,>=3.9
Requires-Dist: sqlalchemy>=2.0.0
